aurora_unicycler/__init__.py
aurora_unicycler/unicycler.py
aurora_unicycler/version.py
aurora_unicycler-0.4.3.dist-info/licenses/LICENSE
aurora_unicycler-0.4.3.dist-info/WHEEL
aurora_unicycler-0.4.3.dist-info/METADATA
aurora_unicycler-0.4.3.dist-info/RECORD
