Metadata-Version: 2.4
Name: aurora-unicycler
Version: 0.4.3
Summary: A universal cycling protocol
Requires-Python: >=3.10
License-Expression: MIT
Classifier: Development Status :: 3 - Alpha
Classifier: Programming Language :: Python :: 3
Classifier: Programming Language :: Python :: 3.10
Classifier: Programming Language :: Python :: 3.11
Classifier: Programming Language :: Python :: 3.12
Classifier: Programming Language :: Python :: 3.13
Classifier: Operating System :: OS Independent
License-File: LICENSE
Requires-Dist: defusedxml>=0.7.1
Requires-Dist: pydantic>=2.11.7
Requires-Dist: bumpver>=2025.1131 ; extra == "dev"
Requires-Dist: pytest>=8.4.1 ; extra == "dev"
Requires-Dist: ruff>=0.12.3 ; extra == "dev"
Requires-Dist: pre-commit>=4.2.0 ; extra == "dev"
Requires-Dist: mkdocs>=1.6.1 ; extra == "dev"
Requires-Dist: mkdocs-material>=9.7.0 ; extra == "dev"
Requires-Dist: mkdocstrings[python]>=0.30.1 ; extra == "dev"
Requires-Dist: pymdown-extensions>=10.17.1 ; extra == "dev"
Provides-Extra: dev
